[
  {
    "full_name": "sveltejs/kit",
    "stargazers_count": 20312,
    "open_issues_count": 1003,
    "forks_count": 2220
  },
  {
    "full_name": "sveltejs/svelte",
    "stargazers_count": 85939,
    "open_issues_count": 973,
    "forks_count": 4785
  },
  {
    "full_name": "withastro/astro",
    "stargazers_count": 57124,
    "open_issues_count": 247,
    "forks_count": 3172
  },
  {
    "full_name": "payloadcms/payload",
    "stargazers_count": 40817,
    "open_issues_count": 728,
    "forks_count": 3406
  },
  {
    "full_name": "tailwindlabs/tailwindcss",
    "stargazers_count": 93808,
    "open_issues_count": 78,
    "forks_count": 5085
  }
]