[
  {
    "full_name": "sveltejs/kit",
    "stargazers_count": 20017,
    "open_issues_count": 1037,
    "forks_count": 2163
  },
  {
    "full_name": "sveltejs/svelte",
    "stargazers_count": 85010,
    "open_issues_count": 960,
    "forks_count": 4696
  },
  {
    "full_name": "withastro/astro",
    "stargazers_count": 54651,
    "open_issues_count": 264,
    "forks_count": 3018
  },
  {
    "full_name": "payloadcms/payload",
    "stargazers_count": 39142,
    "open_issues_count": 826,
    "forks_count": 3153
  },
  {
    "full_name": "tailwindlabs/tailwindcss",
    "stargazers_count": 91320,
    "open_issues_count": 59,
    "forks_count": 4814
  }
]