[
  {
    "full_name": "sveltejs/kit",
    "stargazers_count": 16634,
    "open_issues_count": 658,
    "forks_count": 1645
  },
  {
    "full_name": "sveltejs/svelte",
    "stargazers_count": 74101,
    "open_issues_count": 959,
    "forks_count": 4150
  },
  {
    "full_name": "withastro/astro",
    "stargazers_count": 37310,
    "open_issues_count": 147,
    "forks_count": 1953
  },
  {
    "full_name": "payloadcms/payload",
    "stargazers_count": 14752,
    "open_issues_count": 136,
    "forks_count": 821
  },
  {
    "full_name": "tailwindlabs/tailwindcss",
    "stargazers_count": 73892,
    "open_issues_count": 25,
    "forks_count": 3887
  }
]