[
  {
    "full_name": "sveltejs/kit",
    "stargazers_count": 16517,
    "open_issues_count": 633,
    "forks_count": 1613
  },
  {
    "full_name": "sveltejs/svelte",
    "stargazers_count": 73717,
    "open_issues_count": 927,
    "forks_count": 4101
  },
  {
    "full_name": "withastro/astro",
    "stargazers_count": 36972,
    "open_issues_count": 142,
    "forks_count": 1922
  },
  {
    "full_name": "payloadcms/payload",
    "stargazers_count": 13897,
    "open_issues_count": 107,
    "forks_count": 776
  },
  {
    "full_name": "tailwindlabs/tailwindcss",
    "stargazers_count": 73496,
    "open_issues_count": 17,
    "forks_count": 3849
  }
]