[
  {
    "full_name": "sveltejs/kit",
    "stargazers_count": 17249,
    "open_issues_count": 726,
    "forks_count": 1755
  },
  {
    "full_name": "sveltejs/svelte",
    "stargazers_count": 75394,
    "open_issues_count": 1028,
    "forks_count": 4295
  },
  {
    "full_name": "withastro/astro",
    "stargazers_count": 39806,
    "open_issues_count": 146,
    "forks_count": 2107
  },
  {
    "full_name": "payloadcms/payload",
    "stargazers_count": 17454,
    "open_issues_count": 233,
    "forks_count": 994
  },
  {
    "full_name": "tailwindlabs/tailwindcss",
    "stargazers_count": 76076,
    "open_issues_count": 27,
    "forks_count": 4021
  }
]