[
  {
    "full_name": "rust-lang/rustlings",
    "stargazers_count": 40919,
    "open_issues_count": 129,
    "forks_count": 7413
  },
  {
    "full_name": "BohdanPetryshyn/basti",
    "stargazers_count": 184,
    "open_issues_count": 12,
    "forks_count": 10
  },
  {
    "full_name": "smol-ai/developer",
    "stargazers_count": 10669,
    "open_issues_count": 69,
    "forks_count": 1005
  },
  {
    "full_name": "DefinitelyTyped/DefinitelyTyped",
    "stargazers_count": 44893,
    "open_issues_count": 897,
    "forks_count": 29390
  },
  {
    "full_name": "seb-cr/node-scripting",
    "stargazers_count": 1,
    "open_issues_count": 0,
    "forks_count": 0
  },
  {
    "full_name": "swyxio/ai-notes",
    "stargazers_count": 3602,
    "open_issues_count": 0,
    "forks_count": 268
  },
  {
    "full_name": "statsbomb/open-data",
    "stargazers_count": 1996,
    "open_issues_count": 26,
    "forks_count": 668
  },
  {
    "full_name": "LazyVim/LazyVim",
    "stargazers_count": 7332,
    "open_issues_count": 29,
    "forks_count": 495
  },
  {
    "full_name": "anuraghazra/github-readme-stats",
    "stargazers_count": 58041,
    "open_issues_count": 262,
    "forks_count": 18001
  },
  {
    "full_name": "microsoft/TypeScript",
    "stargazers_count": 93370,
    "open_issues_count": 5921,
    "forks_count": 12063
  },
  {
    "full_name": "skeletonlabs/skeleton",
    "stargazers_count": 3311,
    "open_issues_count": 61,
    "forks_count": 195
  },
  {
    "full_name": "leptos-rs/leptos",
    "stargazers_count": 11298,
    "open_issues_count": 51,
    "forks_count": 385
  },
  {
    "full_name": "jesseduffield/lazydocker",
    "stargazers_count": 29648,
    "open_issues_count": 111,
    "forks_count": 1018
  },
  {
    "full_name": "gelguy/wilder.nvim",
    "stargazers_count": 1074,
    "open_issues_count": 47,
    "forks_count": 26
  },
  {
    "full_name": "nektos/act",
    "stargazers_count": 42042,
    "open_issues_count": 165,
    "forks_count": 1052
  },
  {
    "full_name": "tauri-apps/tauri",
    "stargazers_count": 67627,
    "open_issues_count": 525,
    "forks_count": 1935
  },
  {
    "full_name": "rust-unofficial/awesome-rust",
    "stargazers_count": 36279,
    "open_issues_count": 12,
    "forks_count": 2297
  },
  {
    "full_name": "rothgar/awesome-tuis",
    "stargazers_count": 5146,
    "open_issues_count": 4,
    "forks_count": 172
  },
  {
    "full_name": "soheilpro/mailwind",
    "stargazers_count": 3069,
    "open_issues_count": 3,
    "forks_count": 74
  },
  {
    "full_name": "fathyb/carbonyl",
    "stargazers_count": 13213,
    "open_issues_count": 58,
    "forks_count": 287
  },
  {
    "full_name": "FFmpeg/FFmpeg",
    "stargazers_count": 37761,
    "open_issues_count": 3,
    "forks_count": 11199
  },
  {
    "full_name": "AGWA/git-crypt",
    "stargazers_count": 7451,
    "open_issues_count": 128,
    "forks_count": 473
  },
  {
    "full_name": "dagger/dagger",
    "stargazers_count": 8853,
    "open_issues_count": 386,
    "forks_count": 455
  },
  {
    "full_name": "ankitpokhrel/jira-cli",
    "stargazers_count": 2939,
    "open_issues_count": 50,
    "forks_count": 143
  },
  {
    "full_name": "jesseduffield/lazygit",
    "stargazers_count": 37964,
    "open_issues_count": 530,
    "forks_count": 1497
  },
  {
    "full_name": "vercel/satori",
    "stargazers_count": 8680,
    "open_issues_count": 57,
    "forks_count": 167
  },
  {
    "full_name": "Textualize/textual",
    "stargazers_count": 20403,
    "open_issues_count": 161,
    "forks_count": 623
  },
  {
    "full_name": "microsoft/language-server-protocol",
    "stargazers_count": 9804,
    "open_issues_count": 240,
    "forks_count": 755
  },
  {
    "full_name": "unocss/unocss",
    "stargazers_count": 12851,
    "open_issues_count": 106,
    "forks_count": 614
  },
  {
    "full_name": "payloadcms/payload",
    "stargazers_count": 11784,
    "open_issues_count": 52,
    "forks_count": 634
  }
]