[
  {
    "full_name": "docker-library/official-images",
    "stargazers_count": 6400,
    "open_issues_count": 46,
    "forks_count": 2329
  },
  {
    "full_name": "CopilotC-Nvim/CopilotChat.nvim",
    "stargazers_count": 1445,
    "open_issues_count": 16,
    "forks_count": 67
  },
  {
    "full_name": "syumai/workers",
    "stargazers_count": 618,
    "open_issues_count": 17,
    "forks_count": 39
  },
  {
    "full_name": "gleam-lang/awesome-gleam",
    "stargazers_count": 1190,
    "open_issues_count": 42,
    "forks_count": 65
  },
  {
    "full_name": "gleam-wisp/wisp",
    "stargazers_count": 741,
    "open_issues_count": 11,
    "forks_count": 36
  },
  {
    "full_name": "gleam-lang/gleam",
    "stargazers_count": 17240,
    "open_issues_count": 164,
    "forks_count": 715
  },
  {
    "full_name": "kilimchoi/engineering-blogs",
    "stargazers_count": 31015,
    "open_issues_count": 130,
    "forks_count": 1568
  },
  {
    "full_name": "contourpy/contourpy",
    "stargazers_count": 71,
    "open_issues_count": 8,
    "forks_count": 21
  },
  {
    "full_name": "xddq/ts2typebox",
    "stargazers_count": 41,
    "open_issues_count": 0,
    "forks_count": 1
  },
  {
    "full_name": "serde-rs/serde",
    "stargazers_count": 8956,
    "open_issues_count": 289,
    "forks_count": 755
  },
  {
    "full_name": "Equilibris/nx.nvim",
    "stargazers_count": 91,
    "open_issues_count": 9,
    "forks_count": 15
  },
  {
    "full_name": "opentofu/manifesto",
    "stargazers_count": 36238,
    "open_issues_count": 22,
    "forks_count": 1095
  },
  {
    "full_name": "rust-lang/rustlings",
    "stargazers_count": 52336,
    "open_issues_count": 25,
    "forks_count": 9988
  },
  {
    "full_name": "basti-app/basti",
    "stargazers_count": 319,
    "open_issues_count": 17,
    "forks_count": 18
  },
  {
    "full_name": "smol-ai/developer",
    "stargazers_count": 11784,
    "open_issues_count": 80,
    "forks_count": 1026
  },
  {
    "full_name": "DefinitelyTyped/DefinitelyTyped",
    "stargazers_count": 48107,
    "open_issues_count": 693,
    "forks_count": 30015
  },
  {
    "full_name": "seb-cr/node-scripting",
    "stargazers_count": 1,
    "open_issues_count": 0,
    "forks_count": 0
  },
  {
    "full_name": "swyxio/ai-notes",
    "stargazers_count": 5050,
    "open_issues_count": 2,
    "forks_count": 412
  },
  {
    "full_name": "statsbomb/open-data",
    "stargazers_count": 2407,
    "open_issues_count": 31,
    "forks_count": 760
  },
  {
    "full_name": "LazyVim/LazyVim",
    "stargazers_count": 16310,
    "open_issues_count": 72,
    "forks_count": 1136
  },
  {
    "full_name": "anuraghazra/github-readme-stats",
    "stargazers_count": 67751,
    "open_issues_count": 298,
    "forks_count": 22179
  },
  {
    "full_name": "microsoft/TypeScript",
    "stargazers_count": 99870,
    "open_issues_count": 5673,
    "forks_count": 12360
  },
  {
    "full_name": "skeletonlabs/skeleton",
    "stargazers_count": 4871,
    "open_issues_count": 65,
    "forks_count": 303
  },
  {
    "full_name": "leptos-rs/leptos",
    "stargazers_count": 15731,
    "open_issues_count": 71,
    "forks_count": 616
  },
  {
    "full_name": "jesseduffield/lazydocker",
    "stargazers_count": 36067,
    "open_issues_count": 159,
    "forks_count": 1165
  },
  {
    "full_name": "gelguy/wilder.nvim",
    "stargazers_count": 1335,
    "open_issues_count": 60,
    "forks_count": 35
  },
  {
    "full_name": "nektos/act",
    "stargazers_count": 53537,
    "open_issues_count": 198,
    "forks_count": 1335
  },
  {
    "full_name": "tauri-apps/tauri",
    "stargazers_count": 81329,
    "open_issues_count": 951,
    "forks_count": 2428
  },
  {
    "full_name": "rust-unofficial/awesome-rust",
    "stargazers_count": 45543,
    "open_issues_count": 13,
    "forks_count": 2691
  },
  {
    "full_name": "rothgar/awesome-tuis",
    "stargazers_count": 7408,
    "open_issues_count": 8,
    "forks_count": 255
  }
]